cree_sro_syllabics.py
cree_sro_syllabics-2021.7.26.dist-info/LICENSE
cree_sro_syllabics-2021.7.26.dist-info/WHEEL
cree_sro_syllabics-2021.7.26.dist-info/METADATA
cree_sro_syllabics-2021.7.26.dist-info/RECORD
