Metadata-Version: 2.1
Name: cree-sro-syllabics
Version: 2021.7.26
Summary: Convert between Western Cree SRO and syllabics
Home-page: https://github.com/eddieantonio/cree-sro-syllabics
License: MIT
Author: Eddie Antonio Santos
Author-email: Eddie.Santos@nrc-cnrc.gc.ca
Classifier: Development Status :: 5 - Production/Stable
Classifier: License :: OSI Approved :: MIT License
Classifier: Programming Language :: Python
Classifier: Programming Language :: Python :: 2
Classifier: Programming Language :: Python :: 2.7
Classifier: Programming Language :: Python :: 3
Classifier: Programming Language :: Python :: 3.4
Classifier: Programming Language :: Python :: 3.5
Classifier: Programming Language :: Python :: 3.6
Classifier: Programming Language :: Python :: 3.7
Classifier: Programming Language :: Python :: 3.8
Classifier: Programming Language :: Python :: 3.9
Classifier: Programming Language :: Python :: Implementation :: CPython
Classifier: Programming Language :: Python :: Implementation :: PyPy
Classifier: Topic :: Text Processing :: Linguistic
